managerjson/__init__.py
managerjson/managerjson.py
tests/__init__.py
tests/example_complex_dicts.py
tests/test_jsonmanager.py
managerjson-0.1.6.dist-info/LICENSE
managerjson-0.1.6.dist-info/METADATA
managerjson-0.1.6.dist-info/WHEEL
managerjson-0.1.6.dist-info/top_level.txt
managerjson-0.1.6.dist-info/RECORD
