Metadata-Version: 2.1
Name: managerjson
Version: 0.1.6
Summary: Package to handle complex jsons.
Home-page: https://gitlab.com/osstorres/managerjson
Author: Osiel Torres
Author-email: osieltorresdev@gmail.com
License: UNKNOWN
Platform: UNKNOWN
Classifier: Programming Language :: Python
Classifier: Programming Language :: Python :: 3
Classifier: Development Status :: 5 - Production/Stable
Classifier: License :: OSI Approved :: GNU General Public License v3 (GPLv3)
Classifier: Operating System :: OS Independent
Classifier: Intended Audience :: Developers
Classifier: Natural Language :: English
Requires-Python: >=3
License-File: LICENSE
